georss_ingv_centro_nazionale_terremoti_client/__init__.py
georss_ingv_centro_nazionale_terremoti_client/__version__.py
georss_ingv_centro_nazionale_terremoti_client/consts.py
georss_ingv_centro_nazionale_terremoti_client/feed.py
georss_ingv_centro_nazionale_terremoti_client/feed_entry.py
georss_ingv_centro_nazionale_terremoti_client/feed_manager.py
georss_ingv_centro_nazionale_terremoti_client-0.7.dist-info/LICENSE
georss_ingv_centro_nazionale_terremoti_client-0.7.dist-info/METADATA
georss_ingv_centro_nazionale_terremoti_client-0.7.dist-info/WHEEL
georss_ingv_centro_nazionale_terremoti_client-0.7.dist-info/top_level.txt
georss_ingv_centro_nazionale_terremoti_client-0.7.dist-info/RECORD
