Metadata-Version: 2.1
Name: georss-ingv-centro-nazionale-terremoti-client
Version: 0.7
Summary: A GeoRSS client library for the INGV Centro Nazionale Terremoti (Earthquakes) feed.
Home-page: https://github.com/exxamalte/python-georss-ingv-centro-nazionale-terremoti-client
Author: Malte Franken
Author-email: coding@subspace.de
License: Apache-2.0
Classifier: Programming Language :: Python :: 3.8
Classifier: Programming Language :: Python :: 3.9
Classifier: Programming Language :: Python :: 3.10
Classifier: Programming Language :: Python :: 3.11
Classifier: Programming Language :: Python :: 3.12
Classifier: License :: OSI Approved :: Apache Software License
Classifier: Operating System :: OS Independent
License-File: LICENSE
Requires-Dist: georss-client >=0.17
